{
  "version": 1.3,
  "people": [
    {
      "person_id": [ -1 ],
      "pose_keypoints_2d": [
        -2.655416,
        174.083572,
        0.277678,
        -1.559554,
        162.991714,
        -13.006415,
        -20.922504,
        148.611526,
        -14.051477,
        -28.410597,
        121.186989,
        -6.000657,
        -31.187748,
        97.972183,
        6.456655,
        17.849731,
        150.373062,
        -12.411808,
        26.240519,
        123.547554,
        -3.752159,
        29.457747,
        99.696228,
        7.736217,
        -1.712183,
        110.991043,
        -10.959775,
        -12.720644,
        93.096802,
        -3.914798,
        -14.766313,
        55.447689,
        -3.662749,
        -13.274054,
        12.097318,
        -10.921399,
        11.443187,
        93.498230,
        -3.577025,
        13.896996,
        55.388031,
        -3.479309,
        14.364964,
        12.648077,
        -10.652471,
        -5.299613,
        176.994034,
        -0.832221,
        -0.326744,
        177.351807,
        -0.295791,
        -12.447250,
        175.091660,
        -11.661054,
        7.054415,
        175.771683,
        -10.944581,
        16.731396,
        9.374752,
        -3.075397,
        29.312773,
        94.136513,
        10.298565,
        -30.916954,
        92.375679,
        8.980516,
        -16.071911,
        7.612593,
        -3.460320,
        -1.490967,
        136.159729,
        -11.754937
      ],
      "face_keypoints_2d": [],
      "hand_left_keypoints_2d": [],
      "hand_right_keypoints_2d": [],
      "pose_keypoints_3d": [],
      "face_keypoints_3d": [],
      "hand_left_keypoints_3d": [],
      "hand_right_keypoints_3d": []
    }
  ]
}
